techbeamers/__init__.py
techbeamers/analyzer.py
techbeamers/code_analyzer.py
techbeamers-1.0.1.dist-info/LICENSE.txt
techbeamers-1.0.1.dist-info/METADATA
techbeamers-1.0.1.dist-info/WHEEL
techbeamers-1.0.1.dist-info/entry_points.txt
techbeamers-1.0.1.dist-info/top_level.txt
techbeamers-1.0.1.dist-info/RECORD
