Metadata-Version: 2.1
Name: techbeamers
Version: 1.0.1
Summary: Code Analyzer Tool by TechBeamers
Home-page: https://techbeamers.com
Author: Meenakshi Agarwal
Author-email: magarwal@example.com
Classifier: Programming Language :: Python :: 3
Classifier: License :: OSI Approved :: MIT License
Classifier: Operating System :: OS Independent
License-File: LICENSE.txt
Requires-Dist: pycodestyle
Requires-Dist: flake8
Requires-Dist: mypy
